ckeditor_widget/__init__.py
ckeditor_widget/admin.py
ckeditor_widget/widgets.py
ckeditor_widget/templates/ckeditor_widget/ckeditor.html
django_ckeditor_widget-0.1.dist-info/DESCRIPTION.rst
django_ckeditor_widget-0.1.dist-info/METADATA
django_ckeditor_widget-0.1.dist-info/RECORD
django_ckeditor_widget-0.1.dist-info/WHEEL
django_ckeditor_widget-0.1.dist-info/metadata.json
django_ckeditor_widget-0.1.dist-info/top_level.txt
