Metadata-Version: 2.0
Name: django-ckeditor-widget
Version: 0.1
Summary: A CKEditor widget for Django that includes an admin mixin.
Home-page: https://github.com/Wtower/django-ckeditor-widget
Author: George Karakostas
Author-email: gckarakostas@gmail.com
License: BSD-3 License
Keywords: django ckeditor widget
Platform: UNKNOWN
Classifier: Environment :: Web Environment
Classifier: Framework :: Django
Classifier: Framework :: Django :: 1.11
Classifier: Intended Audience :: Developers
Classifier: License :: OSI Approved :: BSD License
Classifier: Operating System :: OS Independent
Classifier: Programming Language :: Python
Classifier: Programming Language :: Python :: 3
Classifier: Programming Language :: Python :: 3.4
Classifier: Programming Language :: Python :: 3.5
Classifier: Topic :: Internet :: WWW/HTTP
Classifier: Topic :: Internet :: WWW/HTTP :: Dynamic Content
